yadic-0.1.12.6.dist-info/RECORD
yadic-0.1.12.6.dist-info/WHEEL
yadic-0.1.12.6.dist-info/metadata.json
yadic-0.1.12.6.dist-info/DESCRIPTION.rst
yadic-0.1.12.6.dist-info/METADATA
yadic-0.1.12.6.dist-info/top_level.txt
yadic/util.py
yadic/dot.py
yadic/container.py
yadic/browse.py
yadic/__init__.py
yadic/tests/test_util.py
yadic/tests/test_exception.py
yadic/tests/test_container.py
yadic/tests/__init__.py
