Metadata-Version: 2.0
Name: yadic
Version: 0.1.12.6
Summary: Yet Another Dependency Injection Container
